tinyrange_sys/tinyrange
tinyrange_sys/__main__.py
tinyrange_sys/__init__.py
tinyrange_sys/tinyqemu/tinyrange_qemu
tinyrange_sys/tinyqemu/qemu-system-x86_64
tinyrange_sys-0.4.0.dist-info/METADATA
tinyrange_sys-0.4.0.dist-info/WHEEL
tinyrange_sys-0.4.0.dist-info/entry_points.txt
tinyrange_sys-0.4.0.dist-info/RECORD
