Metadata-Version: 2.4
Name: tinyrange_sys
Version: 0.4.0
Summary: TinyRange: Next-generation Virtualization for Cyber and beyond.
License: Apache 2.0
Classifier: License :: OSI Approved :: Apache Software License
Project-URL: Homepage, https://tinyrange.dev
Project-URL: Source Code, https://github.com/tinyrange/tinyrange
Project-URL: Bug Tracker, https://github.com/tinyrange/tinyrange/issues
Requires-Python: ~=3.5
